[
    {
        "user_id": "100001",
        "name": "Kevin Warren",
        "phone": "435-315-3727",
        "score": 42,
        "location": "Snydershire",
        "gender": "female",
        "balance": 37596.8,
        "casa_last_3_months": 7404,
        "birthdate": "1982-04-02"
    },
    {
        "user_id": "100002",
        "name": "Richard Reid",
        "phone": "554.340.9116",
        "score": 56,
        "location": "South Andrewstad",
        "gender": "female",
        "balance": 47304.08,
        "casa_last_3_months": 21302,
        "birthdate": "1997-07-26"
    },
    {
        "user_id": "100003",
        "name": "Julie Moore",
        "phone": "001-551-504-3665",
        "score": 59,
        "location": "West Deniseberg",
        "gender": "female",
        "balance": 5579.63,
        "casa_last_3_months": 19025,
        "birthdate": "1991-02-22"
    },
    {
        "user_id": "100004",
        "name": "Christopher Hanson",
        "phone": "6824905697",
        "score": 67,
        "location": "East Michele",
        "gender": "female",
        "balance": 40659.59,
        "casa_last_3_months": 22383,
        "birthdate": "2001-11-23"
    },
    {
        "user_id": "100005",
        "name": "Johnny Thomas",
        "phone": "572-778-9784",
        "score": 79,
        "location": "North Charles",
        "gender": "female",
        "balance": 15545.26,
        "casa_last_3_months": 13320,
        "birthdate": "2002-01-13"
    },
    {
        "user_id": "100006",
        "name": "Randall Stevens",
        "phone": "(635)252-0924",
        "score": 3,
        "location": "Port Andreachester",
        "gender": "female",
        "balance": 28721.02,
        "casa_last_3_months": 28505,
        "birthdate": "2005-08-16"
    },
    {
        "user_id": "100007",
        "name": "Andrea Klein",
        "phone": "(605)202-4832x67045",
        "score": 92,
        "location": "Changborough",
        "gender": "female",
        "balance": 39242.99,
        "casa_last_3_months": 8738,
        "birthdate": "1986-12-20"
    },
    {
        "user_id": "100008",
        "name": "Mark Byrd",
        "phone": "(229)283-5779",
        "score": 10,
        "location": "Sandraville",
        "gender": "female",
        "balance": 12760.51,
        "casa_last_3_months": 18918,
        "birthdate": "2000-07-16"
    },
    {
        "user_id": "100009",
        "name": "Desiree Brewer",
        "phone": "(689)215-9349",
        "score": 89,
        "location": "Juliatown",
        "gender": "male",
        "balance": 13589.02,
        "casa_last_3_months": 13832,
        "birthdate": "2001-09-08"
    },
    {
        "user_id": "100010",
        "name": "Lance Stanley",
        "phone": "001-689-825-6739x530",
        "score": 24,
        "location": "Cindyside",
        "gender": "male",
        "balance": 33876.96,
        "casa_last_3_months": 12437,
        "birthdate": "1994-08-29"
    },
    {
        "user_id": "100011",
        "name": "Andrea Day",
        "phone": "5354825189",
        "score": 67,
        "location": "Alexisshire",
        "gender": "male",
        "balance": 20024.33,
        "casa_last_3_months": 22984,
        "birthdate": "1975-07-28"
    },
    {
        "user_id": "100012",
        "name": "Kathryn Owen",
        "phone": "875.877.5379x398",
        "score": 57,
        "location": "West Amber",
        "gender": "male",
        "balance": 42172.25,
        "casa_last_3_months": 26811,
        "birthdate": "1978-08-13"
    },
    {
        "user_id": "100013",
        "name": "Ryan Jenkins",
        "phone": "894-429-1841",
        "score": 18,
        "location": "Michelleview",
        "gender": "male",
        "balance": 38473.34,
        "casa_last_3_months": 3026,
        "birthdate": "1977-08-09"
    },
    {
        "user_id": "100014",
        "name": "William Williams",
        "phone": "+1-532-651-0810x87567",
        "score": 45,
        "location": "West Timothy",
        "gender": "male",
        "balance": 13686.3,
        "casa_last_3_months": 6332,
        "birthdate": "1994-08-03"
    },
    {
        "user_id": "100015",
        "name": "Melissa Nguyen",
        "phone": "211-379-4656",
        "score": 18,
        "location": "South Rebecca",
        "gender": "male",
        "balance": 26950.42,
        "casa_last_3_months": 17245,
        "birthdate": "1976-03-05"
    },
    {
        "user_id": "100016",
        "name": "Victor Gonzalez",
        "phone": "001-592-356-2120x63587",
        "score": 82,
        "location": "Robertmouth",
        "gender": "male",
        "balance": 1796.39,
        "casa_last_3_months": 23302,
        "birthdate": "2002-07-29"
    },
    {
        "user_id": "100017",
        "name": "Joe Williamson",
        "phone": "+1-737-747-7961x4362",
        "score": 95,
        "location": "Jamesland",
        "gender": "male",
        "balance": 40882.34,
        "casa_last_3_months": 22588,
        "birthdate": "1974-06-03"
    },
    {
        "user_id": "100018",
        "name": "Melvin Anderson",
        "phone": "378-757-3741",
        "score": 98,
        "location": "Riverafort",
        "gender": "male",
        "balance": 27661.1,
        "casa_last_3_months": 20927,
        "birthdate": "1981-04-22"
    },
    {
        "user_id": "100019",
        "name": "Mary Meyers",
        "phone": "001-312-201-6749x58342",
        "score": 62,
        "location": "New Johnville",
        "gender": "female",
        "balance": 14644.49,
        "casa_last_3_months": 13859,
        "birthdate": "2001-09-22"
    },
    {
        "user_id": "100020",
        "name": "Brent Garrett",
        "phone": "952.254.2602x97729",
        "score": 33,
        "location": "Cassandramouth",
        "gender": "male",
        "balance": 11503.99,
        "casa_last_3_months": 17717,
        "birthdate": "1989-07-16"
    },
    {
        "user_id": "100021",
        "name": "David Sawyer",
        "phone": "7239950897",
        "score": 28,
        "location": "Wilsontown",
        "gender": "female",
        "balance": 35760.12,
        "casa_last_3_months": 29700,
        "birthdate": "1992-04-28"
    },
    {
        "user_id": "100022",
        "name": "Jennifer Lyons",
        "phone": "+1-598-480-1131x89251",
        "score": 14,
        "location": "Brownborough",
        "gender": "male",
        "balance": 6217.72,
        "casa_last_3_months": 4776,
        "birthdate": "1990-03-12"
    },
    {
        "user_id": "100023",
        "name": "Kenneth Christensen",
        "phone": "(805)255-5000x0475",
        "score": 86,
        "location": "Jonesmouth",
        "gender": "female",
        "balance": 20123.3,
        "casa_last_3_months": 18130,
        "birthdate": "1976-07-28"
    },
    {
        "user_id": "100024",
        "name": "William Tapia",
        "phone": "329.321.2969",
        "score": 75,
        "location": "South Monicaview",
        "gender": "female",
        "balance": 30762.4,
        "casa_last_3_months": 6893,
        "birthdate": "1981-10-21"
    },
    {
        "user_id": "100025",
        "name": "Kevin Shepard",
        "phone": "7703494191",
        "score": 11,
        "location": "Port Kyle",
        "gender": "female",
        "balance": 7225.74,
        "casa_last_3_months": 17837,
        "birthdate": "2005-12-22"
    },
    {
        "user_id": "100026",
        "name": "Jonathan Davis",
        "phone": "581-886-0458",
        "score": 80,
        "location": "Lake Sarahland",
        "gender": "male",
        "balance": 35703.91,
        "casa_last_3_months": 28472,
        "birthdate": "1998-11-12"
    },
    {
        "user_id": "100027",
        "name": "Sherry Clarke",
        "phone": "(852)582-9360x28473",
        "score": 6,
        "location": "South Jason",
        "gender": "male",
        "balance": 45453.08,
        "casa_last_3_months": 29051,
        "birthdate": "1985-11-08"
    },
    {
        "user_id": "100028",
        "name": "Mary Hill",
        "phone": "001-337-451-3954",
        "score": 84,
        "location": "Susanview",
        "gender": "male",
        "balance": 10341.93,
        "casa_last_3_months": 17341,
        "birthdate": "1991-11-06"
    },
    {
        "user_id": "100029",
        "name": "Erica Becker",
        "phone": "766.826.1248x1417",
        "score": 63,
        "location": "Rhondaton",
        "gender": "female",
        "balance": 32020.2,
        "casa_last_3_months": 29241,
        "birthdate": "1978-05-08"
    },
    {
        "user_id": "100030",
        "name": "Laura Howell",
        "phone": "372-636-1169x850",
        "score": 4,
        "location": "Lake John",
        "gender": "female",
        "balance": 30507.22,
        "casa_last_3_months": 18380,
        "birthdate": "2005-07-20"
    },
    {
        "user_id": "100031",
        "name": "Gerald Austin",
        "phone": "662.333.6863x164",
        "score": 96,
        "location": "Joneston",
        "gender": "female",
        "balance": 34555.6,
        "casa_last_3_months": 8171,
        "birthdate": "1979-01-10"
    },
    {
        "user_id": "100032",
        "name": "Robert Murillo",
        "phone": "990-435-9905x554",
        "score": 48,
        "location": "South Zachary",
        "gender": "female",
        "balance": 27259.82,
        "casa_last_3_months": 13199,
        "birthdate": "2001-04-03"
    },
    {
        "user_id": "100033",
        "name": "Alexander Olson",
        "phone": "+1-833-486-8207x179",
        "score": 39,
        "location": "Port Richard",
        "gender": "female",
        "balance": 5326.61,
        "casa_last_3_months": 18412,
        "birthdate": "1995-04-23"
    },
    {
        "user_id": "100034",
        "name": "Jeffrey Ferguson",
        "phone": "(257)367-2804x92031",
        "score": 51,
        "location": "West Vincent",
        "gender": "female",
        "balance": 48490.79,
        "casa_last_3_months": 11380,
        "birthdate": "2005-11-17"
    },
    {
        "user_id": "100035",
        "name": "Tara Perkins",
        "phone": "(699)311-5475",
        "score": 66,
        "location": "Hallview",
        "gender": "female",
        "balance": 20092.09,
        "casa_last_3_months": 3073,
        "birthdate": "1984-05-19"
    },
    {
        "user_id": "100036",
        "name": "Brittany Zamora",
        "phone": "+1-295-276-6659",
        "score": 91,
        "location": "Williamside",
        "gender": "female",
        "balance": 1270.47,
        "casa_last_3_months": 7693,
        "birthdate": "1976-04-19"
    },
    {
        "user_id": "100037",
        "name": "Rita Dunlap",
        "phone": "657.540.6764x828",
        "score": 55,
        "location": "Staceyview",
        "gender": "female",
        "balance": 31929.42,
        "casa_last_3_months": 7551,
        "birthdate": "2004-01-02"
    },
    {
        "user_id": "100038",
        "name": "Brianna Gray",
        "phone": "284.742.7298x77441",
        "score": 66,
        "location": "North Tanya",
        "gender": "male",
        "balance": 5896.15,
        "casa_last_3_months": 25260,
        "birthdate": "1999-07-31"
    },
    {
        "user_id": "100039",
        "name": "Cassie Gomez",
        "phone": "+1-579-294-3675",
        "score": 35,
        "location": "Margaretville",
        "gender": "male",
        "balance": 26183.33,
        "casa_last_3_months": 9206,
        "birthdate": "1985-07-13"
    },
    {
        "user_id": "100040",
        "name": "Scott Rodriguez",
        "phone": "001-366-590-7632x844",
        "score": 83,
        "location": "Lake Tracishire",
        "gender": "male",
        "balance": 5047.41,
        "casa_last_3_months": 8987,
        "birthdate": "1998-08-12"
    },
    {
        "user_id": "100041",
        "name": "Kathleen Meza",
        "phone": "+1-765-770-5357x23294",
        "score": 79,
        "location": "New Karenton",
        "gender": "female",
        "balance": 6514.52,
        "casa_last_3_months": 15681,
        "birthdate": "1984-02-09"
    },
    {
        "user_id": "100042",
        "name": "Dr. Tyler Garrison",
        "phone": "001-484-258-9733x423",
        "score": 54,
        "location": "Briannaside",
        "gender": "female",
        "balance": 15176.15,
        "casa_last_3_months": 14548,
        "birthdate": "2004-07-08"
    },
    {
        "user_id": "100043",
        "name": "Troy Miller",
        "phone": "319.460.9121",
        "score": 76,
        "location": "Amychester",
        "gender": "female",
        "balance": 29788.05,
        "casa_last_3_months": 4674,
        "birthdate": "1979-07-30"
    },
    {
        "user_id": "100044",
        "name": "Donald Jacobs",
        "phone": "513.619.5929",
        "score": 60,
        "location": "West Amymouth",
        "gender": "female",
        "balance": 33588.72,
        "casa_last_3_months": 29302,
        "birthdate": "1976-11-30"
    },
    {
        "user_id": "100045",
        "name": "Kimberly Obrien",
        "phone": "001-554-358-7076x18213",
        "score": 43,
        "location": "New Travis",
        "gender": "female",
        "balance": 2006.53,
        "casa_last_3_months": 28625,
        "birthdate": "1997-11-28"
    },
    {
        "user_id": "100046",
        "name": "Kristin Greene",
        "phone": "919-876-9459x63830",
        "score": 44,
        "location": "South Stevenborough",
        "gender": "male",
        "balance": 27623.66,
        "casa_last_3_months": 17708,
        "birthdate": "1975-02-27"
    },
    {
        "user_id": "100047",
        "name": "Matthew Richards",
        "phone": "494-616-5465x72841",
        "score": 84,
        "location": "South Timothyborough",
        "gender": "female",
        "balance": 1867.09,
        "casa_last_3_months": 14733,
        "birthdate": "1998-11-23"
    },
    {
        "user_id": "100048",
        "name": "Gabriel Mack",
        "phone": "001-905-884-8301x015",
        "score": 82,
        "location": "Joshuaberg",
        "gender": "female",
        "balance": 7382.91,
        "casa_last_3_months": 11103,
        "birthdate": "1983-12-28"
    },
    {
        "user_id": "100049",
        "name": "Christopher Robinson",
        "phone": "7512859619",
        "score": 9,
        "location": "Heatherport",
        "gender": "male",
        "balance": 7778.56,
        "casa_last_3_months": 9993,
        "birthdate": "1986-08-31"
    },
    {
        "user_id": "100050",
        "name": "Craig Jackson",
        "phone": "588.422.8230",
        "score": 38,
        "location": "Foxstad",
        "gender": "male",
        "balance": 43267.56,
        "casa_last_3_months": 18321,
        "birthdate": "1981-08-02"
    },
    {
        "user_id": "100051",
        "name": "Patrick Haas",
        "phone": "7767034322",
        "score": 89,
        "location": "North Michaelton",
        "gender": "male",
        "balance": 20190.54,
        "casa_last_3_months": 17121,
        "birthdate": "1987-08-27"
    },
    {
        "user_id": "100052",
        "name": "Valerie Taylor",
        "phone": "718.206.8467x7396",
        "score": 16,
        "location": "Lake Ronaldtown",
        "gender": "male",
        "balance": 35977.5,
        "casa_last_3_months": 5384,
        "birthdate": "1975-10-28"
    },
    {
        "user_id": "100053",
        "name": "Kenneth Chang DDS",
        "phone": "438-396-2495x028",
        "score": 18,
        "location": "Vincentstad",
        "gender": "female",
        "balance": 48439.84,
        "casa_last_3_months": 22423,
        "birthdate": "2005-09-06"
    },
    {
        "user_id": "100054",
        "name": "Christian Hartman",
        "phone": "(740)460-3150",
        "score": 62,
        "location": "Masseyburgh",
        "gender": "male",
        "balance": 11105.85,
        "casa_last_3_months": 18675,
        "birthdate": "1998-08-16"
    },
    {
        "user_id": "100055",
        "name": "Deborah Phillips",
        "phone": "746.394.9623x3824",
        "score": 11,
        "location": "West Seanshire",
        "gender": "female",
        "balance": 7398.51,
        "casa_last_3_months": 11995,
        "birthdate": "2001-06-10"
    },
    {
        "user_id": "100056",
        "name": "Roy Johnson",
        "phone": "+1-250-300-3256x99406",
        "score": 21,
        "location": "East Jacobhaven",
        "gender": "male",
        "balance": 45633.99,
        "casa_last_3_months": 15093,
        "birthdate": "1982-11-25"
    },
    {
        "user_id": "100057",
        "name": "Alexa Swanson",
        "phone": "6569864711",
        "score": 62,
        "location": "North Patrick",
        "gender": "male",
        "balance": 11152.07,
        "casa_last_3_months": 22320,
        "birthdate": "1987-08-06"
    },
    {
        "user_id": "100058",
        "name": "Michael Franklin",
        "phone": "(678)766-7134",
        "score": 38,
        "location": "Michaelview",
        "gender": "male",
        "balance": 46501.55,
        "casa_last_3_months": 27708,
        "birthdate": "2003-02-18"
    },
    {
        "user_id": "100059",
        "name": "Thomas Graham",
        "phone": "001-916-474-7598x2127",
        "score": 75,
        "location": "Kellyburgh",
        "gender": "female",
        "balance": 29979.26,
        "casa_last_3_months": 16189,
        "birthdate": "1976-07-19"
    },
    {
        "user_id": "100060",
        "name": "Lydia Delgado",
        "phone": "001-768-695-9412x289",
        "score": 78,
        "location": "Williamsborough",
        "gender": "male",
        "balance": 45613.3,
        "casa_last_3_months": 27773,
        "birthdate": "1982-10-31"
    },
    {
        "user_id": "100061",
        "name": "Casey Bennett",
        "phone": "(486)643-6761",
        "score": 17,
        "location": "Mikaylamouth",
        "gender": "female",
        "balance": 47080.77,
        "casa_last_3_months": 18444,
        "birthdate": "2005-04-15"
    },
    {
        "user_id": "100062",
        "name": "Stephanie Wells",
        "phone": "972-287-8507",
        "score": 61,
        "location": "North Michaelbury",
        "gender": "male",
        "balance": 16849.76,
        "casa_last_3_months": 6292,
        "birthdate": "1980-01-30"
    },
    {
        "user_id": "100063",
        "name": "Leah Graham",
        "phone": "+1-475-987-7313",
        "score": 76,
        "location": "West Keithmouth",
        "gender": "male",
        "balance": 24362.41,
        "casa_last_3_months": 21196,
        "birthdate": "1979-05-13"
    },
    {
        "user_id": "100064",
        "name": "Curtis Collins",
        "phone": "001-775-901-9884x21421",
        "score": 50,
        "location": "Burnettchester",
        "gender": "male",
        "balance": 693.97,
        "casa_last_3_months": 15752,
        "birthdate": "1997-05-19"
    },
    {
        "user_id": "100065",
        "name": "Sheila Foster",
        "phone": "3477433045",
        "score": 92,
        "location": "West Michael",
        "gender": "male",
        "balance": 21060.43,
        "casa_last_3_months": 3752,
        "birthdate": "1975-01-20"
    },
    {
        "user_id": "100066",
        "name": "Robin Douglas",
        "phone": "001-683-933-6014x183",
        "score": 5,
        "location": "North Sarah",
        "gender": "female",
        "balance": 47355.24,
        "casa_last_3_months": 28403,
        "birthdate": "1985-09-24"
    },
    {
        "user_id": "100067",
        "name": "Felicia Taylor",
        "phone": "001-713-882-7748x3192",
        "score": 18,
        "location": "West Mariaborough",
        "gender": "male",
        "balance": 44427.71,
        "casa_last_3_months": 15860,
        "birthdate": "1975-07-01"
    },
    {
        "user_id": "100068",
        "name": "Jacob Salazar",
        "phone": "+1-821-277-3308",
        "score": 47,
        "location": "Port Brandyhaven",
        "gender": "male",
        "balance": 14973.71,
        "casa_last_3_months": 15843,
        "birthdate": "2002-11-26"
    },
    {
        "user_id": "100069",
        "name": "Zachary Mckinney",
        "phone": "001-773-736-3302",
        "score": 33,
        "location": "New Ashleyville",
        "gender": "male",
        "balance": 31298.15,
        "casa_last_3_months": 23185,
        "birthdate": "2006-01-08"
    },
    {
        "user_id": "100070",
        "name": "Elizabeth Rivera",
        "phone": "(282)258-4478",
        "score": 7,
        "location": "Palmerton",
        "gender": "male",
        "balance": 19974.11,
        "casa_last_3_months": 17985,
        "birthdate": "1998-09-15"
    },
    {
        "user_id": "100071",
        "name": "Michael Vazquez",
        "phone": "001-554-538-5383x9089",
        "score": 78,
        "location": "Lake Laurenfurt",
        "gender": "male",
        "balance": 12678.33,
        "casa_last_3_months": 22536,
        "birthdate": "2006-08-03"
    },
    {
        "user_id": "100072",
        "name": "David Reed",
        "phone": "(437)818-3045x888",
        "score": 82,
        "location": "West Charlesstad",
        "gender": "male",
        "balance": 35803.18,
        "casa_last_3_months": 23121,
        "birthdate": "1992-08-30"
    },
    {
        "user_id": "100073",
        "name": "Robert Mack",
        "phone": "(824)638-2030x8794",
        "score": 61,
        "location": "New Williamland",
        "gender": "female",
        "balance": 6587.78,
        "casa_last_3_months": 11201,
        "birthdate": "1994-01-15"
    },
    {
        "user_id": "100074",
        "name": "Megan Richards",
        "phone": "(698)504-5948",
        "score": 29,
        "location": "North Katherine",
        "gender": "male",
        "balance": 23420.46,
        "casa_last_3_months": 5913,
        "birthdate": "1997-10-03"
    },
    {
        "user_id": "100075",
        "name": "Bridget Davis",
        "phone": "603.291.8831x2222",
        "score": 3,
        "location": "Diazport",
        "gender": "female",
        "balance": 32181.5,
        "casa_last_3_months": 13696,
        "birthdate": "1978-05-24"
    },
    {
        "user_id": "100076",
        "name": "Madison Douglas",
        "phone": "001-984-976-6738",
        "score": 32,
        "location": "East Ashleystad",
        "gender": "female",
        "balance": 6324.82,
        "casa_last_3_months": 21823,
        "birthdate": "1979-08-07"
    },
    {
        "user_id": "100077",
        "name": "Matthew Powell",
        "phone": "+1-901-640-4165x65476",
        "score": 88,
        "location": "Castillomouth",
        "gender": "male",
        "balance": 6126.24,
        "casa_last_3_months": 18419,
        "birthdate": "1975-05-30"
    },
    {
        "user_id": "100078",
        "name": "Cynthia Quinn",
        "phone": "+1-649-853-4359x979",
        "score": 25,
        "location": "Port Leefort",
        "gender": "male",
        "balance": 19638.66,
        "casa_last_3_months": 3867,
        "birthdate": "2000-10-19"
    },
    {
        "user_id": "100079",
        "name": "Robert Hunt",
        "phone": "+1-371-889-1144x989",
        "score": 35,
        "location": "Veronicaview",
        "gender": "male",
        "balance": 46250.18,
        "casa_last_3_months": 7705,
        "birthdate": "1992-05-31"
    },
    {
        "user_id": "100080",
        "name": "Alexis Patel",
        "phone": "001-364-405-8468x480",
        "score": 91,
        "location": "Bishoptown",
        "gender": "female",
        "balance": 28135.46,
        "casa_last_3_months": 23040,
        "birthdate": "1992-03-28"
    },
    {
        "user_id": "100081",
        "name": "Jessica Potter",
        "phone": "(329)891-7301",
        "score": 90,
        "location": "Lake Anna",
        "gender": "female",
        "balance": 11756.3,
        "casa_last_3_months": 16075,
        "birthdate": "1997-11-28"
    },
    {
        "user_id": "100082",
        "name": "Tara Paul",
        "phone": "(233)366-3574x45070",
        "score": 13,
        "location": "Stevenschester",
        "gender": "male",
        "balance": 47278.73,
        "casa_last_3_months": 22554,
        "birthdate": "2003-01-10"
    },
    {
        "user_id": "100083",
        "name": "Jasmine Brown",
        "phone": "986-517-1863",
        "score": 75,
        "location": "Torresside",
        "gender": "male",
        "balance": 36075.64,
        "casa_last_3_months": 25464,
        "birthdate": "1980-12-18"
    },
    {
        "user_id": "100084",
        "name": "Katherine Schultz",
        "phone": "(846)429-3738",
        "score": 42,
        "location": "Cannonland",
        "gender": "female",
        "balance": 37570.65,
        "casa_last_3_months": 15427,
        "birthdate": "1983-08-06"
    },
    {
        "user_id": "100085",
        "name": "Michael Blair",
        "phone": "4529878716",
        "score": 18,
        "location": "Kristitown",
        "gender": "male",
        "balance": 42771.08,
        "casa_last_3_months": 14888,
        "birthdate": "1989-08-25"
    },
    {
        "user_id": "100086",
        "name": "Kevin Molina",
        "phone": "+1-412-758-1773",
        "score": 38,
        "location": "Matthewhaven",
        "gender": "male",
        "balance": 22546.1,
        "casa_last_3_months": 11959,
        "birthdate": "1995-05-27"
    },
    {
        "user_id": "100087",
        "name": "Dawn Cook",
        "phone": "+1-649-804-6755x25747",
        "score": 66,
        "location": "New Shaneshire",
        "gender": "male",
        "balance": 11165.5,
        "casa_last_3_months": 7159,
        "birthdate": "1997-11-29"
    },
    {
        "user_id": "100088",
        "name": "Hannah Warren",
        "phone": "+1-423-357-8612x0019",
        "score": 67,
        "location": "Ryanborough",
        "gender": "male",
        "balance": 19560.48,
        "casa_last_3_months": 8179,
        "birthdate": "1998-05-14"
    },
    {
        "user_id": "100089",
        "name": "Larry Hughes",
        "phone": "(547)455-6841x14798",
        "score": 34,
        "location": "Fritzstad",
        "gender": "female",
        "balance": 15637.78,
        "casa_last_3_months": 27329,
        "birthdate": "1981-04-20"
    },
    {
        "user_id": "100090",
        "name": "Michael Owen",
        "phone": "3566473761",
        "score": 4,
        "location": "East Cindy",
        "gender": "female",
        "balance": 10261.8,
        "casa_last_3_months": 3792,
        "birthdate": "1989-05-17"
    },
    {
        "user_id": "100091",
        "name": "Susan Mayo",
        "phone": "(589)374-5782",
        "score": 6,
        "location": "Clarkmouth",
        "gender": "male",
        "balance": 31358.99,
        "casa_last_3_months": 21829,
        "birthdate": "2003-01-27"
    },
    {
        "user_id": "100092",
        "name": "Brian Woods",
        "phone": "(292)201-1555x4085",
        "score": 19,
        "location": "East Jameschester",
        "gender": "female",
        "balance": 40832.7,
        "casa_last_3_months": 24092,
        "birthdate": "1982-12-28"
    },
    {
        "user_id": "100093",
        "name": "Jamie Thompson",
        "phone": "001-685-722-9569x407",
        "score": 19,
        "location": "Longville",
        "gender": "male",
        "balance": 32914.27,
        "casa_last_3_months": 12543,
        "birthdate": "1986-10-09"
    },
    {
        "user_id": "100094",
        "name": "Michelle Hancock",
        "phone": "612.351.1517x727",
        "score": 94,
        "location": "West Brenda",
        "gender": "female",
        "balance": 33900.17,
        "casa_last_3_months": 24893,
        "birthdate": "1996-07-21"
    },
    {
        "user_id": "100095",
        "name": "Shannon Reyes",
        "phone": "001-349-978-5559",
        "score": 79,
        "location": "Lake Veronicaburgh",
        "gender": "female",
        "balance": 46512.81,
        "casa_last_3_months": 22235,
        "birthdate": "1992-05-29"
    },
    {
        "user_id": "100096",
        "name": "James Patel II",
        "phone": "(259)955-3259x893",
        "score": 35,
        "location": "Christopherstad",
        "gender": "female",
        "balance": 6850.36,
        "casa_last_3_months": 28054,
        "birthdate": "1990-08-23"
    },
    {
        "user_id": "100097",
        "name": "Sarah White",
        "phone": "564.222.2243x048",
        "score": 88,
        "location": "Anthonyberg",
        "gender": "male",
        "balance": 41166.76,
        "casa_last_3_months": 26021,
        "birthdate": "2001-06-10"
    },
    {
        "user_id": "100098",
        "name": "Amanda Smith",
        "phone": "942.706.3994x4825",
        "score": 18,
        "location": "East Timothystad",
        "gender": "female",
        "balance": 36764.52,
        "casa_last_3_months": 29092,
        "birthdate": "1991-12-01"
    },
    {
        "user_id": "100099",
        "name": "Courtney Ramsey",
        "phone": "4734413581",
        "score": 23,
        "location": "Martinezville",
        "gender": "male",
        "balance": 48041.59,
        "casa_last_3_months": 20193,
        "birthdate": "1977-11-01"
    },
    {
        "user_id": "100100",
        "name": "Kelsey Malone",
        "phone": "001-424-491-9388x48732",
        "score": 57,
        "location": "East Morganshire",
        "gender": "male",
        "balance": 48196.19,
        "casa_last_3_months": 3955,
        "birthdate": "1987-02-16"
    },
    {
        "user_id": "100101",
        "name": "Ryan Nelson",
        "phone": "001-824-335-0538",
        "score": 6,
        "location": "Kimton",
        "gender": "female",
        "balance": 31104.33,
        "casa_last_3_months": 21920,
        "birthdate": "2004-11-06"
    },
    {
        "user_id": "100102",
        "name": "Bernard Green",
        "phone": "(901)203-8988x26239",
        "score": 39,
        "location": "Lake Lauren",
        "gender": "male",
        "balance": 49642.16,
        "casa_last_3_months": 29166,
        "birthdate": "1974-11-02"
    },
    {
        "user_id": "100103",
        "name": "Randy Whitaker",
        "phone": "+1-531-616-6373",
        "score": 61,
        "location": "West Jeanette",
        "gender": "female",
        "balance": 29710.63,
        "casa_last_3_months": 23946,
        "birthdate": "2005-04-22"
    },
    {
        "user_id": "100104",
        "name": "Stephanie Norton",
        "phone": "(415)990-1084",
        "score": 88,
        "location": "West Helen",
        "gender": "male",
        "balance": 47633.51,
        "casa_last_3_months": 8911,
        "birthdate": "1991-03-17"
    },
    {
        "user_id": "100105",
        "name": "Elizabeth Castro",
        "phone": "690-854-5996x19894",
        "score": 64,
        "location": "Lambville",
        "gender": "male",
        "balance": 13183.5,
        "casa_last_3_months": 24503,
        "birthdate": "1992-01-14"
    },
    {
        "user_id": "100106",
        "name": "Sandra Martin",
        "phone": "001-337-570-5000x12828",
        "score": 77,
        "location": "Perezbury",
        "gender": "male",
        "balance": 15487.73,
        "casa_last_3_months": 14886,
        "birthdate": "1999-12-08"
    },
    {
        "user_id": "100107",
        "name": "Kimberly Green",
        "phone": "998.702.2875x5712",
        "score": 7,
        "location": "West Robertland",
        "gender": "male",
        "balance": 41720.37,
        "casa_last_3_months": 24509,
        "birthdate": "2000-04-26"
    },
    {
        "user_id": "100108",
        "name": "Craig Davis",
        "phone": "683.202.4748x51517",
        "score": 23,
        "location": "West Dianamouth",
        "gender": "female",
        "balance": 9623.28,
        "casa_last_3_months": 16168,
        "birthdate": "1990-05-08"
    },
    {
        "user_id": "100109",
        "name": "Jonathan Peterson",
        "phone": "001-451-893-9397x18730",
        "score": 8,
        "location": "West Barrymouth",
        "gender": "female",
        "balance": 3153.84,
        "casa_last_3_months": 5880,
        "birthdate": "1998-07-14"
    },
    {
        "user_id": "100110",
        "name": "Christina Carter",
        "phone": "711-410-6151x93807",
        "score": 21,
        "location": "Maryburgh",
        "gender": "female",
        "balance": 45880.24,
        "casa_last_3_months": 7201,
        "birthdate": "1984-03-12"
    },
    {
        "user_id": "100111",
        "name": "Sara Park",
        "phone": "7672399113",
        "score": 14,
        "location": "South Steven",
        "gender": "female",
        "balance": 14455.61,
        "casa_last_3_months": 28863,
        "birthdate": "1999-02-21"
    },
    {
        "user_id": "100112",
        "name": "Ashley Ramos",
        "phone": "(532)576-3268x642",
        "score": 91,
        "location": "Lake Robinhaven",
        "gender": "male",
        "balance": 1124.01,
        "casa_last_3_months": 17268,
        "birthdate": "1977-11-01"
    },
    {
        "user_id": "100113",
        "name": "Victoria Montes",
        "phone": "(507)477-6802",
        "score": 43,
        "location": "Jenniferburgh",
        "gender": "male",
        "balance": 37307.76,
        "casa_last_3_months": 8586,
        "birthdate": "1977-03-23"
    },
    {
        "user_id": "100114",
        "name": "Christopher Gregory",
        "phone": "437.526.5718",
        "score": 40,
        "location": "Jessicachester",
        "gender": "male",
        "balance": 47928.67,
        "casa_last_3_months": 4578,
        "birthdate": "1999-10-22"
    },
    {
        "user_id": "100115",
        "name": "Joseph Roberts",
        "phone": "+1-775-469-7403x418",
        "score": 77,
        "location": "South Madisonchester",
        "gender": "male",
        "balance": 46328.11,
        "casa_last_3_months": 14676,
        "birthdate": "2005-02-17"
    },
    {
        "user_id": "100116",
        "name": "Sherri Austin",
        "phone": "5438566551",
        "score": 64,
        "location": "North William",
        "gender": "female",
        "balance": 9597.39,
        "casa_last_3_months": 24356,
        "birthdate": "1994-09-29"
    },
    {
        "user_id": "100117",
        "name": "Frank Roberts",
        "phone": "(390)612-9286",
        "score": 67,
        "location": "Wadechester",
        "gender": "male",
        "balance": 44547.23,
        "casa_last_3_months": 1213,
        "birthdate": "1993-04-18"
    },
    {
        "user_id": "100118",
        "name": "Joel Morrison",
        "phone": "(323)849-8582",
        "score": 67,
        "location": "Elaineberg",
        "gender": "female",
        "balance": 17606.3,
        "casa_last_3_months": 29925,
        "birthdate": "1998-09-27"
    },
    {
        "user_id": "100119",
        "name": "Alexander Pacheco",
        "phone": "+1-674-942-1478x99910",
        "score": 50,
        "location": "Perkinsmouth",
        "gender": "female",
        "balance": 12237.67,
        "casa_last_3_months": 11774,
        "birthdate": "1996-09-24"
    },
    {
        "user_id": "100120",
        "name": "Kevin Taylor",
        "phone": "334-707-2981x1772",
        "score": 65,
        "location": "Deanfurt",
        "gender": "male",
        "balance": 16432.78,
        "casa_last_3_months": 23293,
        "birthdate": "2000-02-03"
    },
    {
        "user_id": "100121",
        "name": "Sean Soto",
        "phone": "604-930-5850x50072",
        "score": 87,
        "location": "Lake Jenniferchester",
        "gender": "female",
        "balance": 27976.32,
        "casa_last_3_months": 9133,
        "birthdate": "1993-12-01"
    },
    {
        "user_id": "100122",
        "name": "Rose Robinson",
        "phone": "+1-966-613-3431",
        "score": 14,
        "location": "Wileyshire",
        "gender": "male",
        "balance": 40603.56,
        "casa_last_3_months": 22114,
        "birthdate": "1994-12-29"
    },
    {
        "user_id": "100123",
        "name": "Virginia Stevenson",
        "phone": "001-323-293-3721x475",
        "score": 40,
        "location": "Brandonstad",
        "gender": "male",
        "balance": 29376.8,
        "casa_last_3_months": 8047,
        "birthdate": "1977-04-19"
    },
    {
        "user_id": "100124",
        "name": "Samuel Warner",
        "phone": "+1-529-810-0181",
        "score": 12,
        "location": "New Joshua",
        "gender": "male",
        "balance": 947.09,
        "casa_last_3_months": 15643,
        "birthdate": "1982-11-02"
    },
    {
        "user_id": "100125",
        "name": "Shannon Barker",
        "phone": "501-549-3325",
        "score": 74,
        "location": "New Ambershire",
        "gender": "female",
        "balance": 10404.41,
        "casa_last_3_months": 22843,
        "birthdate": "1986-07-10"
    },
    {
        "user_id": "100126",
        "name": "Mary Wheeler",
        "phone": "001-826-980-8344x5403",
        "score": 51,
        "location": "New Brandon",
        "gender": "male",
        "balance": 5401.22,
        "casa_last_3_months": 14919,
        "birthdate": "2005-04-26"
    },
    {
        "user_id": "100127",
        "name": "Miranda Spencer",
        "phone": "(226)357-2666x755",
        "score": 39,
        "location": "Rebeccabury",
        "gender": "female",
        "balance": 46896.13,
        "casa_last_3_months": 11423,
        "birthdate": "2002-03-23"
    },
    {
        "user_id": "100128",
        "name": "Adam Ramos",
        "phone": "587-202-2602x06984",
        "score": 5,
        "location": "New Andrea",
        "gender": "male",
        "balance": 18447.97,
        "casa_last_3_months": 29849,
        "birthdate": "2004-09-23"
    },
    {
        "user_id": "100129",
        "name": "Mr. Timothy Conway",
        "phone": "496.276.0818x9063",
        "score": 49,
        "location": "East Stephanieberg",
        "gender": "male",
        "balance": 33832.72,
        "casa_last_3_months": 18258,
        "birthdate": "1983-11-08"
    },
    {
        "user_id": "100130",
        "name": "Dennis Garcia",
        "phone": "462-804-0725x41871",
        "score": 29,
        "location": "Cookbury",
        "gender": "male",
        "balance": 27625.16,
        "casa_last_3_months": 10512,
        "birthdate": "2003-06-09"
    },
    {
        "user_id": "100131",
        "name": "Terri Martinez",
        "phone": "+1-400-478-6943x83010",
        "score": 70,
        "location": "New James",
        "gender": "male",
        "balance": 40521.15,
        "casa_last_3_months": 28226,
        "birthdate": "1974-01-31"
    },
    {
        "user_id": "100132",
        "name": "Jesse Brown",
        "phone": "838.540.2986",
        "score": 61,
        "location": "South Lisa",
        "gender": "female",
        "balance": 13695.47,
        "casa_last_3_months": 20026,
        "birthdate": "1974-05-15"
    },
    {
        "user_id": "100133",
        "name": "Brian Myers",
        "phone": "(650)514-3889x08728",
        "score": 76,
        "location": "Lake Brianfort",
        "gender": "male",
        "balance": 47356.2,
        "casa_last_3_months": 14455,
        "birthdate": "1994-06-21"
    }
]